{
  "format_version": "1.0",
  "term": [
    {
      "id": "1",
      "name": "山本8号",
      "data_intr_time": 600,
      "data": [
        {
          "date": "20260708124412",
          "power_voltage": "12.0",
          "sensu15xx": {
            "temp": 27.9,
            "cumtemp": 2272.4,
            "humi": 74.0,
            "uv": 1750,
            "uvi": 4,
            "illumi": 62334.0,
            "rain": 0.0,
            "rain_1h": 0.0,
            "rain_24h": 0.0,
            "rain_bgn": 0.0,
            "wind_dir": 313,
            "wind_dir_str": "北西",
            "wind_speed": 1.0,
            "max_wind_speed": 3.5,
            "wbgt": 28,
            "wbgt_str": "厳重警戒"
          },
          "atmos": 997,
          "sea_level_pressure": 1013
        }
      ]
    }
  ]
}