{
  "format_version": "1.0",
  "term": [
    {
      "id": "1",
      "name": "山本8号",
      "data_intr_time": 600,
      "data": [
        {
          "date": "20260702024040",
          "power_voltage": "11.9",
          "sensu15xx": {
            "temp": 22.3,
            "cumtemp": 2132.6,
            "humi": 97.0,
            "uv": 0,
            "uvi": 0,
            "illumi": 0.0,
            "rain": 0.3,
            "rain_1h": 1.2,
            "rain_24h": 109.2,
            "rain_bgn": 109.2,
            "wind_dir": 77,
            "wind_dir_str": "東北東",
            "wind_speed": 0.4,
            "max_wind_speed": 2.0,
            "wbgt": 22,
            "wbgt_str": "注意"
          },
          "atmos": 990,
          "sea_level_pressure": 1006
        }
      ]
    }
  ]
}